creassessment/__init__.py
creassessment/controler/__init__.py
creassessment/controler/app.py
creassessment/controler/constants.py
creassessment/grader/__init__.py
creassessment/grader/codemaster_analyzer.py
creassessment/grader/creativity/__init__.py
creassessment/grader/creativity/creativity_grader.py
creassessment/grader/creativity/flexibility/__init__.py
creassessment/grader/creativity/flexibility/flexibility_components.py
creassessment/grader/creativity/flexibility/flexibility_functionalities.py
creassessment/grader/creativity/flexibility/flexibility_grader.py
creassessment/grader/creativity/flexibility/flexibility_programming.py
creassessment/grader/creativity/fluency/__init__.py
creassessment/grader/creativity/fluency/fluency_components.py
creassessment/grader/creativity/fluency/fluency_grader.py
creassessment/grader/creativity/fluency/fluency_programming.py
creassessment/grader/creativity/originality/__init__.py
creassessment/grader/creativity/originality/originality_UI_components.py
creassessment/grader/creativity/originality/originality_functionalities.py
creassessment/grader/creativity/originality/originality_grader.py
creassessment/grader/creativity/originality/originality_tags.py
creassessment/grader/creativity/originality/originality_topic.py
creassessment/grader/creativity/reference_universes/__init__.py
creassessment/grader/creativity/reference_universes/reference_universe.py
creassessment/grader/creativity/reference_universes/fluency/__init__.py
creassessment/grader/creativity/reference_universes/fluency/reference_universe_components.py
creassessment/grader/creativity/reference_universes/fluency/reference_universe_components_99993apps.py
creassessment/grader/creativity/reference_universes/fluency/reference_universe_programming.py
creassessment/grader/creativity/reference_universes/fluency/reference_universe_programming_99993apps.py
creassessment/grader/creativity/reference_universes/originality/__init__.py
creassessment-1.9.4.dist-info/LICENCE
creassessment-1.9.4.dist-info/METADATA
creassessment-1.9.4.dist-info/WHEEL
creassessment-1.9.4.dist-info/top_level.txt
creassessment-1.9.4.dist-info/RECORD
