Metadata-Version: 2.1
Name: creassessment
Version: 1.9.4
Summary: An App Inventor app creativity assessment package
Author: Nathalia
Author-email: nathaliacruzalves@gmail.com
Classifier: Programming Language :: Python :: 3
Classifier: License :: OSI Approved :: MIT License
Classifier: Operating System :: OS Independent
Requires-Python: >=3.6
License-File: LICENCE
Requires-Dist: yake ==0.4.8
